{"nodes": [{"id": "05_ket_luan_index", "label": "Ch\u01b0\u01a1ng 5 \u2014 K\u1ebft lu\u1eadn", "file_type": "document", "source_file": "thesis/chapters/05_ket_luan/index.md"}], "edges": [{"source": "05_ket_luan_index", "target": "05_ket_luan_5_1_ket_qua_doi_chieu_voi_muc_tieu", "relation": "references", "confidence": "EXTRACTED", "confidence_score": 1.0, "source_file": "thesis/chapters/05_ket_luan/index.md"}, {"source": "05_ket_luan_index", "target": "05_ket_luan_5_2_cac_van_de_con_ton_dong", "relation": "references", "confidence": "EXTRACTED", "confidence_score": 1.0, "source_file": "thesis/chapters/05_ket_luan/index.md"}, {"source": "05_ket_luan_index", "target": "05_ket_luan_5_3_mo_rong_huong_phat_trien", "relation": "references", "confidence": "EXTRACTED", "confidence_score": 1.0, "source_file": "thesis/chapters/05_ket_luan/index.md"}], "hyperedges": []}